cdm/__init__.py
cdm/enums/__init__.py
cdm/enums/azure_cloud_endpoint.py
cdm/enums/cdm_attribute_context_type.py
cdm/enums/cdm_data_format.py
cdm/enums/cdm_incremental_partition_type.py
cdm/enums/cdm_log_code.py
cdm/enums/cdm_object_type.py
cdm/enums/cdm_operation_type.py
cdm/enums/cdm_relationship_discovery_style.py
cdm/enums/cdm_status_level.py
cdm/enums/cdm_validation_step.py
cdm/enums/environment_type.py
cdm/enums/imports_load_strategy.py
cdm/enums/partition_file_status_check_type.py
cdm/enums/utils.py
cdm/objectmodel/__init__.py
cdm/objectmodel/_document_library.py
cdm/objectmodel/_import_priorities.py
cdm/objectmodel/cdm_argument_collection.py
cdm/objectmodel/cdm_argument_def.py
cdm/objectmodel/cdm_argument_value.py
cdm/objectmodel/cdm_attribute_context.py
cdm/objectmodel/cdm_attribute_context_ref.py
cdm/objectmodel/cdm_attribute_def.py
cdm/objectmodel/cdm_attribute_group_def.py
cdm/objectmodel/cdm_attribute_group_ref.py
cdm/objectmodel/cdm_attribute_item.py
cdm/objectmodel/cdm_attribute_ref.py
cdm/objectmodel/cdm_attribute_resolution_guidance_def.py
cdm/objectmodel/cdm_collection.py
cdm/objectmodel/cdm_constant_entity_def.py
cdm/objectmodel/cdm_container_def.py
cdm/objectmodel/cdm_corpus_context.py
cdm/objectmodel/cdm_corpus_def.py
cdm/objectmodel/cdm_data_partition_def.py
cdm/objectmodel/cdm_data_partition_pattern_def.py
cdm/objectmodel/cdm_data_type_def.py
cdm/objectmodel/cdm_data_type_ref.py
cdm/objectmodel/cdm_definition_collection.py
cdm/objectmodel/cdm_document_collection.py
cdm/objectmodel/cdm_document_def.py
cdm/objectmodel/cdm_e2e_relationship.py
cdm/objectmodel/cdm_entity_attribute_def.py
cdm/objectmodel/cdm_entity_collection.py
cdm/objectmodel/cdm_entity_declaration_def.py
cdm/objectmodel/cdm_entity_def.py
cdm/objectmodel/cdm_entity_ref.py
cdm/objectmodel/cdm_file_status.py
cdm/objectmodel/cdm_folder_collection.py
cdm/objectmodel/cdm_folder_def.py
cdm/objectmodel/cdm_import.py
cdm/objectmodel/cdm_import_collection.py
commondatamodel_objectmodel-1.7.6.dist-info/METADATA
commondatamodel_objectmodel-1.7.6.dist-info/WHEEL
commondatamodel_objectmodel-1.7.6.dist-info/top_level.txt
commondatamodel_objectmodel-1.7.6.dist-info/RECORD
