Metadata-Version: 2.1
Name: commondatamodel-objectmodel
Version: 1.7.6
Summary: Common Data Model Object Model library for Python
Home-page: https://github.com/microsoft/CDM/tree/master/objectModel/Python
Author: Microsoft
Author-email: UNKNOWN
License: UNKNOWN
Platform: UNKNOWN
Classifier: Programming Language :: Python :: 3.5
Classifier: License :: OSI Approved :: MIT License
Classifier: Operating System :: OS Independent
Requires-Dist: nest-asyncio <2,>=1.4.3
Requires-Dist: msal <2,>=1.14.0
Requires-Dist: python-dateutil >=2.8.0
Requires-Dist: msrest >=0.6.21
Requires-Dist: regex >=2020.11.13
Requires-Dist: commondatamodel-objectmodel-cdmstandards >=2.8.0
